oss/core/__init__.py
oss/core/bin/__init__.py
oss/core/bin/argumentparser.py
oss/core/log.py
oss/core/message.py
oss/core/models/__init__.py
oss/core/models/base/__init__.py
oss/core/models/base/app.py
oss/core/models/base/buzzer.py
oss/core/models/base/discipline.py
oss/core/models/base/remote.py
oss/core/models/base/timer.py
oss/core/models/buzzers.py
oss/core/models/discipline/__init__.py
oss/core/models/discipline/configurations/__init__.py
oss/core/models/discipline/configurations/air_rifle_10m.json
oss/core/models/discipline/configurations/europees_praktijk_parcours.json
oss/core/models/discipline/configurations/service_pistool.json
oss/core/models/discipline/multi_stage.py
oss/core/models/discipline/single_stage.py
oss/core/models/timers.py
openshootingsolutions_core-0.0.1.dist-info/LICENSE
openshootingsolutions_core-0.0.1.dist-info/METADATA
openshootingsolutions_core-0.0.1.dist-info/WHEEL
openshootingsolutions_core-0.0.1.dist-info/RECORD
