Metadata-Version: 2.1
Name: openshootingsolutions-core
Version: 0.0.1
Summary: OSS core package
License: GPL-3.0-or-later
Author: Arnoud Stolk
Requires-Python: >=3.12,<4.0
Classifier: License :: OSI Approved :: GNU General Public License v3 or later (GPLv3+)
Classifier: Programming Language :: Python :: 3
Classifier: Programming Language :: Python :: 3.12
Classifier: Programming Language :: Python :: 3.13
Requires-Dist: pika (>=1.3.2,<2.0.0)
Requires-Dist: pydantic (>=2.8.2,<3.0.0)
Requires-Dist: python-dotenv (>=1.0.1,<2.0.0)
